dogeek_cli/__init__.py
dogeek_cli/__main__.py
dogeek_cli/app.py
dogeek_cli/client.py
dogeek_cli/config.py
dogeek_cli/enums.py
dogeek_cli/formatter.py
dogeek_cli/logging.py
dogeek_cli/meta.py
dogeek_cli/plugin.py
dogeek_cli/state.py
dogeek_cli/subcommands/__init__.py
dogeek_cli/subcommands/config.py
dogeek_cli/subcommands/env.py
dogeek_cli/subcommands/plugins.py
dogeek_cli/subcommands/registry.py
dogeek_cli/subcommands/system.py
dogeek_cli/templates/plugin/.cliignore.mako
dogeek_cli/templates/plugin/__init__.py.mako
dogeek_cli/templates/plugin/main.py.mako
dogeek_cli/utils.py
dogeek_cli-1.5.0.dist-info/entry_points.txt
dogeek_cli-1.5.0.dist-info/LICENSE
dogeek_cli-1.5.0.dist-info/WHEEL
dogeek_cli-1.5.0.dist-info/METADATA
dogeek_cli-1.5.0.dist-info/RECORD
