Metadata-Version: 2.1
Name: dogeek-cli
Version: 1.5.0
Summary: Interactive CLI to store scripts into
License: MIT
Author: Dogeek
Author-email: simon.bordeyne@gmail.com
Requires-Python: >=3.10,<4.0
Classifier: License :: OSI Approved :: MIT License
Classifier: Programming Language :: Python :: 3
Classifier: Programming Language :: Python :: 3.10
Classifier: Programming Language :: Python :: 3.10
Classifier: Programming Language :: Python :: 3.7
Classifier: Programming Language :: Python :: 3.8
Classifier: Programming Language :: Python :: 3.9
Requires-Dist: Mako (>=1.2.1,<2.0.0)
Requires-Dist: PyYAML (>=6.0,<7.0)
Requires-Dist: cryptography[ssh] (>=37.0.4,<38.0.0)
Requires-Dist: gitignore-parser (>=0.0.8,<0.0.9)
Requires-Dist: pick (>=1.4.0,<2.0.0)
Requires-Dist: requests (>=2.28.1,<3.0.0)
Requires-Dist: toml (>=0.10.2,<0.11.0)
Requires-Dist: typer[all] (>=0.6.1,<0.7.0)
Requires-Dist: xdgconfig (>=1.3.0,<2.0.0)
